alertsActor/__init__.py
alertsActor/alerts_main.py
alertsActor/cmds/__init__.py
alertsActor/cmds/acknowledge.py
alertsActor/cmds/cheatSheet.py
alertsActor/cmds/cmd_parser.py
alertsActor/cmds/disable.py
alertsActor/cmds/enable.py
alertsActor/cmds/instrumentState.py
alertsActor/cmds/ping.py
alertsActor/cmds/status.py
alertsActor/cmds/unacknowledge.py
alertsActor/cmds/version.py
alertsActor/core/__init__.py
alertsActor/core/exceptions.py
alertsActor/etc/alertActions.yml
alertsActor/etc/alerts.cfg
alertsActor/etc/alertsActor.yml
alertsActor/misc/__init__.py
alertsActor/misc/color_print.py
alertsActor/misc/logger.py
alertsActor/rules/__init__.py
alertsActor/rules/callbackWrapper.py
alertsActor/rules/dangerKey.py
alertsActor/rules/mail.py
alertsActor/rules/sms.py
alertsActor/tests/__init__.py
alertsActor/tests/conftest.py
alertsActor/tests/test_main.py
alertsActor/utils/__init__.py
alertsActor/utils/color_print.py
alertsActor/utils/logger.py
sdss_alertsActor-2.1.6.data/scripts/alertsActor
sdss_alertsActor-2.1.6.data/scripts/alerts_main.py
sdss_alertsActor-2.1.6.dist-info/LICENSE.md
sdss_alertsActor-2.1.6.dist-info/METADATA
sdss_alertsActor-2.1.6.dist-info/WHEEL
sdss_alertsActor-2.1.6.dist-info/top_level.txt
sdss_alertsActor-2.1.6.dist-info/RECORD
