Metadata-Version: 2.1
Name: sdss-alertsActor
Version: 2.1.6
Summary: actor for monitoring and raising alerts in SDSS
Home-page: https://github.com/sdss/tron
Author: John Donor
Maintainer: John Donor
Maintainer-email: j.donor@tcu.edu
License: BSD 3-Clause License
Project-URL: Repository, https://github.com/sdss/twistedAlertsActor
Keywords: astronomy,software
Platform: UNKNOWN
Classifier: Intended Audience :: Science/Research
Classifier: Natural Language :: English
Classifier: Operating System :: OS Independent
Classifier: Programming Language :: Python
Classifier: Programming Language :: Python :: 3.7
Classifier: Topic :: Software Development :: Libraries :: Python Modules
Requires-Python: >=3.7
Requires-Dist: pyyaml
Requires-Dist: pygments
Requires-Dist: sdss-opscore
Requires-Dist: twilio
Requires-Dist: click (<=6.7)
Requires-Dist: pyparsing
Requires-Dist: sdsstools
Requires-Dist: sdss-twistedActor
Provides-Extra: dev
Requires-Dist: ipython (>=7.13.0) ; extra == 'dev'
Requires-Dist: pytest (>=3.0.7) ; extra == 'dev'
Requires-Dist: pytest-cov (>=2.4.0) ; extra == 'dev'
Requires-Dist: pytest-sugar (>=0.8.0) ; extra == 'dev'
